LICENSE
MANIFEST.in
README.rst
changelog.rst
setup.cfg
setup.py
hancock/.__init__.py.swp
hancock/__init__.py
hancock/__init__.pyc
hancock.egg-info/PKG-INFO
hancock.egg-info/SOURCES.txt
hancock.egg-info/dependency_links.txt
hancock.egg-info/requires.txt
hancock.egg-info/top_level.txt
hancock/__pycache__/__init__.cpython-34.pyc