Metadata-Version: 1.1
Name: hancock
Version: 1.1.1
Summary: HTTP request signing library.Provides private key URL signing for secure HTTP requests.
Home-page: http://pypi.python.org/pypi/hancock
Author: Justin Wilson
Author-email: justinwilson1@gmail.com
License: Simplified BSD
Platform: UNKNOWN
Classifier: Development Status :: 5 - Production/Stable
Classifier: Intended Audience :: Developers
Classifier: Topic :: Utilities
Classifier: License :: OSI Approved :: BSD License
Classifier: Natural Language :: English
Classifier: Programming Language :: Python
Classifier: Programming Language :: Python :: 2.7
Classifier: Programming Language :: Python :: 3
Classifier: Programming Language :: Python :: 3.3
Classifier: Programming Language :: Python :: 3.4
